LarkBot/LarkBot.py
LarkBot/__init__.py
LarkBot-0.0.3.dist-info/METADATA
LarkBot-0.0.3.dist-info/WHEEL
LarkBot-0.0.3.dist-info/top_level.txt
LarkBot-0.0.3.dist-info/RECORD
